capabilitymesh/__init__.py
capabilitymesh/mesh.py
capabilitymesh/core/__init__.py
capabilitymesh/core/exceptions.py
capabilitymesh/core/identity.py
capabilitymesh/core/types.py
capabilitymesh/discovery/__init__.py
capabilitymesh/embeddings/__init__.py
capabilitymesh/embeddings/base.py
capabilitymesh/embeddings/keyword.py
capabilitymesh/embeddings/local.py
capabilitymesh/embeddings/openai.py
capabilitymesh/integrations/__init__.py
capabilitymesh/integrations/autogen.py
capabilitymesh/integrations/base.py
capabilitymesh/integrations/crewai.py
capabilitymesh/integrations/langgraph.py
capabilitymesh/integrations/a2a/__init__.py
capabilitymesh/integrations/a2a/adapter.py
capabilitymesh/integrations/a2a/client.py
capabilitymesh/integrations/a2a/converter.py
capabilitymesh/negotiation/__init__.py
capabilitymesh/schemas/__init__.py
capabilitymesh/schemas/capability.py
capabilitymesh/storage/__init__.py
capabilitymesh/storage/base.py
capabilitymesh/storage/memory.py
capabilitymesh/storage/redis.py
capabilitymesh/storage/sqlite.py
capabilitymesh/trust/__init__.py
capabilitymesh/trust/simple.py
capabilitymesh-1.0.0a2.dist-info/licenses/LICENSE
capabilitymesh-1.0.0a2.dist-info/licenses/NOTICE
capabilitymesh-1.0.0a2.dist-info/METADATA
capabilitymesh-1.0.0a2.dist-info/WHEEL
capabilitymesh-1.0.0a2.dist-info/top_level.txt
capabilitymesh-1.0.0a2.dist-info/RECORD
