Metadata-Version: 2.4
Name: capabilitymesh
Version: 1.0.0a2
Summary: Universal capability discovery and negotiation for multi-agent systems - works across all frameworks
Author-email: Sai Kumar Yava <saikumar.geek@github.com>
License: Apache-2.0
Project-URL: Homepage, https://github.com/scionoftech/capabilitymesh
Project-URL: Documentation, https://scionoftech.github.io/capabilitymesh
Project-URL: Repository, https://github.com/scionoftech/capabilitymesh
Project-URL: Issues, https://github.com/scionoftech/capabilitymesh/issues
Keywords: agents,multi-agent,capability,discovery,negotiation,ai,llm,a2a,crewai,autogen,langgraph,agent-framework,capability-mesh,agent-discovery,agent-negotiation
Classifier: Development Status :: 3 - Alpha
Classifier: Intended Audience :: Developers
Classifier: License :: OSI Approved :: Apache Software License
Classifier: Programming Language :: Python :: 3
Classifier: Programming Language :: Python :: 3.9
Classifier: Programming Language :: Python :: 3.10
Classifier: Programming Language :: Python :: 3.11
Classifier: Programming Language :: Python :: 3.12
Classifier: Topic :: Software Development :: Libraries :: Python Modules
Classifier: Topic :: Scientific/Engineering :: Artificial Intelligence
Requires-Python: >=3.9
License-File: LICENSE
License-File: NOTICE
Requires-Dist: pydantic>=2.0.0
Requires-Dist: httpx>=0.25.0
Requires-Dist: cryptography>=41.0.0
Requires-Dist: pyjwt>=2.8.0
Requires-Dist: nest-asyncio>=1.5.0
Provides-Extra: grpc
Requires-Dist: grpcio>=1.59.0; extra == "grpc"
Requires-Dist: grpcio-tools>=1.59.0; extra == "grpc"
Provides-Extra: mqtt
Requires-Dist: paho-mqtt>=1.6.1; extra == "mqtt"
Provides-Extra: embeddings
Requires-Dist: sentence-transformers>=2.2.0; extra == "embeddings"
Provides-Extra: openai
Requires-Dist: openai>=1.0.0; extra == "openai"
Provides-Extra: sqlite
Requires-Dist: aiosqlite>=0.19.0; extra == "sqlite"
Provides-Extra: redis
Requires-Dist: redis[asyncio]>=5.0.0; extra == "redis"
Provides-Extra: a2a
Requires-Dist: httpx>=0.25.0; extra == "a2a"
Provides-Extra: crewai
Requires-Dist: crewai>=0.40.0; extra == "crewai"
Provides-Extra: langgraph
Requires-Dist: langgraph>=0.2.0; extra == "langgraph"
Requires-Dist: langchain>=0.1.0; extra == "langgraph"
Provides-Extra: autogen
Requires-Dist: pyautogen>=0.2.0; extra == "autogen"
Provides-Extra: llamaindex
Requires-Dist: llama-index>=0.10.0; extra == "llamaindex"
Provides-Extra: haystack
Requires-Dist: haystack-ai>=2.0.0; extra == "haystack"
Provides-Extra: frameworks
Requires-Dist: capabilitymesh[a2a,autogen,crewai,langgraph]; extra == "frameworks"
Provides-Extra: all
Requires-Dist: capabilitymesh[embeddings,frameworks,grpc,haystack,llamaindex,mqtt,redis,sqlite]; extra == "all"
Provides-Extra: dev
Requires-Dist: pytest>=7.4.0; extra == "dev"
Requires-Dist: pytest-asyncio>=0.21.0; extra == "dev"
Requires-Dist: pytest-cov>=4.1.0; extra == "dev"
Requires-Dist: black>=23.0.0; extra == "dev"
Requires-Dist: ruff>=0.1.0; extra == "dev"
Requires-Dist: mypy>=1.6.0; extra == "dev"
Requires-Dist: types-pyjwt; extra == "dev"
Dynamic: license-file
